[
    {
        "word":  "farm",
        "korean":  "농장",
        "english":  "",
        "example":  ""
    },
    {
        "word":  "chicken",
        "korean":  "닭",
        "english":  "",
        "example":  ""
    },
    {
        "word":  "afraid",
        "korean":  "두려워하는",
        "english":  "",
        "example":  ""
    },
    {
        "word":  "bet - bet",
        "korean":  "장담하다",
        "english":  "",
        "example":  ""
    },
    {
        "word":  "crowded",
        "korean":  "붐비는",
        "english":  "",
        "example":  ""
    },
    {
        "word":  "get - got",
        "korean":  "이르다, 도달하다",
        "english":  "",
        "example":  ""
    },
    {
        "word":  "bus",
        "korean":  "버스",
        "english":  "",
        "example":  ""
    },
    {
        "word":  "train",
        "korean":  "기차",
        "english":  "",
        "example":  ""
    },
    {
        "word":  "scenery",
        "korean":  "경치, 풍경",
        "english":  "",
        "example":  ""
    },
    {
        "word":  "weather forecast",
        "korean":  "일기예보",
        "english":  "",
        "example":  ""
    },
    {
        "word":  "waterfall",
        "korean":  "폭포",
        "english":  "",
        "example":  ""
    },
    {
        "word":  "beautiful",
        "korean":  "아름다운",
        "english":  "",
        "example":  ""
    }
]
